dart_physics/__init__.py
dart_physics/dirs.py
dart_physics/new_server2.py
dart_physics/perf_check.py
dart_physics/server.py
dart_physics/avp_stream3/__init__.py
dart_physics/avp_stream3/grpc_avp_client.py
dart_physics/avp_stream3/grpc_aws_server.py
dart_physics/avp_stream3/grpc_msg/__init__.py
dart_physics/avp_stream3/grpc_msg/dexterity_pb2.py
dart_physics/avp_stream3/grpc_msg/dexterity_pb2_grpc.py
dart_physics/avp_stream3/grpc_msg/handtracking_pb2.py
dart_physics/avp_stream3/grpc_msg/handtracking_pb2_grpc.py
dart_physics/avp_stream3/utils/__init__.py
dart_physics/avp_stream3/utils/grpc_utils.py
dart_physics/avp_stream3/utils/isaac_utils.py
dart_physics/avp_stream3/utils/se3_utils.py
dart_physics/avp_stream3/utils/trn_constants.py
dart_physics/cfgs/__init__.py
dart_physics/cfgs/bimanual_insertion.png
dart_physics/cfgs/bimanual_insertion.py
dart_physics/cfgs/bolt_nut_sort.png
dart_physics/cfgs/bolt_nut_sort.py
dart_physics/cfgs/cvs_travel_sort.png
dart_physics/cfgs/cvs_travel_sort.py
dart_physics/cfgs/dummy.yaml
dart_physics/cfgs/handover.py
dart_physics/cfgs/hang_things_on_wall.png
dart_physics/cfgs/hang_things_on_wall.py
dart_physics/cfgs/jenga.png
dart_physics/cfgs/jenga.py
dart_physics/cfgs/lego.png
dart_physics/cfgs/lego.py
dart_physics/cfgs/magna.py
dart_physics/cfgs/mug_hang.png
dart_physics/cfgs/mug_hang.yaml
dart_physics/cfgs/new_mug_hang.py
dart_physics/cfgs/organize_desk.png
dart_physics/cfgs/organize_desk.yaml
dart_physics/cfgs/piano.png
dart_physics/cfgs/piano.yaml
dart_physics/cfgs/pyramid.png
dart_physics/cfgs/pyramid.py
dart_physics/cfgs/rubiks_cube.png
dart_physics/cfgs/rubiks_cube.yaml
dart_physics/cfgs/scene.xml
dart_physics/cfgs/table_bookshelf.py
dart_physics/cfgs/test.py
dart_physics/cfgs/toy_five_insertions.png
dart_physics/cfgs/toy_five_insertions.py
dart_physics/mink/__init__.py
dart_physics/mink/configuration.py
dart_physics/mink/constants.py
dart_physics/mink/exceptions.py
dart_physics/mink/py.typed
dart_physics/mink/solve_ik.py
dart_physics-2.1.14.dist-info/METADATA
dart_physics-2.1.14.dist-info/WHEEL
dart_physics-2.1.14.dist-info/top_level.txt
dart_physics-2.1.14.dist-info/RECORD
