Metadata-Version: 2.2
Name: dart_physics
Version: 2.1.14
Author: Younghyo Park
Author-email: younghyo@mit.edu
Requires-Python: >=3.6
Requires-Dist: mujoco
Requires-Dist: gdown
Requires-Dist: adam-robotics[jax]==0.3.0
Requires-Dist: dm_control
Requires-Dist: loop_rate_limiters
Requires-Dist: avp_stream
Requires-Dist: robot_descriptions
Requires-Dist: obj2mjcf
Requires-Dist: flask>=3.0.3
Requires-Dist: psutil
Requires-Dist: mediapy
Requires-Dist: pyzmq
Requires-Dist: grpcio
Requires-Dist: grpcio-tools
Requires-Dist: numpy
Requires-Dist: imageio>=2.36.0
Requires-Dist: opencv-python
Requires-Dist: qpsolvers[quadprog]>=4.3.1
Requires-Dist: typing_extensions
Requires-Dist: dexhub-api>=0.3
Requires-Dist: gdown
Dynamic: author
Dynamic: author-email
Dynamic: requires-dist
Dynamic: requires-python
